Metadata-Version: 2.4
Name: xpart
Version: 0.23.8
Summary: Generation of Particle Ensembles
Home-page: https://xsuite.readthedocs.io/
Download-URL: https://pypi.python.org/pypi/xpart
Author: G. Iadarola et al.
License: Apache 2.0
Project-URL: Bug Tracker, https://github.com/xsuite/xsuite/issues
Project-URL: Documentation, https://xsuite.readthedocs.io/
Project-URL: Source Code, https://github.com/xsuite/xpart
License-File: LICENSE
Requires-Dist: numpy>=1.0
Requires-Dist: scipy
Requires-Dist: xobjects
Requires-Dist: xtrack
Provides-Extra: tests
Requires-Dist: cpymad; extra == "tests"
Requires-Dist: PyHEADTAIL; extra == "tests"
Requires-Dist: pytest; extra == "tests"
Dynamic: author
Dynamic: description
Dynamic: download-url
Dynamic: home-page
Dynamic: license
Dynamic: license-file
Dynamic: project-url
Dynamic: provides-extra
Dynamic: requires-dist
Dynamic: summary
